synonymes/__init__.py
synonymes/synonymes.py
synonymes-0.0.3.3.dist-info/LICENSE
synonymes-0.0.3.3.dist-info/METADATA
synonymes-0.0.3.3.dist-info/WHEEL
synonymes-0.0.3.3.dist-info/top_level.txt
synonymes-0.0.3.3.dist-info/RECORD
