Metadata-Version: 2.1
Name: synonymes
Version: 0.0.3.3
Summary: Une librairie pour trouver les synonymes d'un mot
Home-page: https://github.com/mino260806
Author: Amin Guermazi
Author-email: mino260806@gmail.com
License: UNKNOWN
Platform: UNKNOWN
Classifier: Programming Language :: Python :: 3
Classifier: License :: OSI Approved :: GNU General Public License v3 (GPLv3)
Classifier: Operating System :: OS Independent
Requires-Python: >=3.6
Requires-Dist: beautifulsoup4
Requires-Dist: unidecode
Requires-Dist: requests
